suq/SUQ_MLP.py
suq/SUQ_ViT.py
suq/__init__.py
suq/base_suq.py
suq/diag_suq_mlp.py
suq/diag_suq_transformer.py
suq/streamline_layer.py
suq-0.1.0.dist-info/licenses/LICENSE
suq-0.1.0.dist-info/METADATA
suq-0.1.0.dist-info/WHEEL
suq-0.1.0.dist-info/top_level.txt
suq-0.1.0.dist-info/RECORD
