Metadata-Version: 2.4
Name: suq
Version: 0.1.0
Summary: Streamlined Uncertainty Quantification (SUQ)
Home-page: https://github.com/AaltoML/SUQ
Author: Rui Li, Marcus Klasson, Arno Solin, Martin Trapp
License: MIT
Classifier: Programming Language :: Python :: 3
License-File: LICENSE
Requires-Dist: torch>=1.10
Requires-Dist: numpy>=1.21
Requires-Dist: tqdm>=4.60
Dynamic: author
Dynamic: classifier
Dynamic: home-page
Dynamic: license
Dynamic: license-file
Dynamic: requires-dist
Dynamic: summary
